edne_correios_loader/__about__.py
edne_correios_loader/__init__.py
edne_correios_loader/cep_querier.py
edne_correios_loader/dbwriter.py
edne_correios_loader/exc.py
edne_correios_loader/loader.py
edne_correios_loader/resolver.py
edne_correios_loader/table_set.py
edne_correios_loader/tables.py
edne_correios_loader/unified_table.py
edne_correios_loader/cli/__init__.py
edne_correios_loader/cli/logger.py
edne_correios_loader-0.1.3.dist-info/METADATA
edne_correios_loader-0.1.3.dist-info/WHEEL
edne_correios_loader-0.1.3.dist-info/entry_points.txt
edne_correios_loader-0.1.3.dist-info/licenses/LICENSE.txt
edne_correios_loader-0.1.3.dist-info/RECORD
