Metadata-Version: 2.3
Name: edne-correios-loader
Version: 0.1.3
Summary: Load Brazilian Correios' e-DNE Basico text files into your database to enable CEP search
Project-URL: Documentation, https://github.com/cauethenorio/edne-correios-loader#readme
Project-URL: Issues, https://github.com/cauethenorio/edne-correios-loader/issues
Project-URL: Source, https://github.com/cauethenorio/edne-correios-loader
Author-email: Cauê Thenório <caue@thenorio.com.br>
License-Expression: MIT
License-File: LICENSE.txt
Keywords: Brasil,CEP,Correios,DNE,address,eDNE,endereço
Classifier: Development Status :: 4 - Beta
Classifier: Programming Language :: Python
Classifier: Programming Language :: Python :: 3.8
Classifier: Programming Language :: Python :: 3.9
Classifier: Programming Language :: Python :: 3.10
Classifier: Programming Language :: Python :: 3.11
Classifier: Programming Language :: Python :: 3.12
Classifier: Programming Language :: Python :: Implementation :: CPython
Classifier: Programming Language :: Python :: Implementation :: PyPy
Requires-Python: >=3.8
Requires-Dist: click~=8.1
Requires-Dist: sqlalchemy~=2.0
Requires-Dist: toposort~=1.1; python_version < '3.9'
Provides-Extra: mysql
Requires-Dist: pymysql; extra == 'mysql'
Provides-Extra: postgresql
Requires-Dist: psycopg2-binary; extra == 'postgresql'
